aws_proxy/__init__.py
aws_proxy/config.py
aws_proxy/client/__init__.py
aws_proxy/client/auth_proxy.py
aws_proxy/client/cli.py
aws_proxy/client/http2_server.py
aws_proxy/client/utils.py
aws_proxy/server/__init__.py
aws_proxy/server/aws_request_forwarder.py
aws_proxy/server/extension.py
aws_proxy/server/request_handler.py
aws_proxy/server/ui/__init__.py
aws_proxy/server/ui/app.js
aws_proxy/server/ui/favicon.png
aws_proxy/server/ui/index.html
aws_proxy/shared/__init__.py
aws_proxy/shared/constants.py
aws_proxy/shared/models.py
aws_proxy/shared/utils.py
tests/__init__.py
tests/conftest.py
tests/test_config.py
tests/test_proxy_requests.py
localstack_extension_aws_proxy-0.2.1.dist-info/METADATA
localstack_extension_aws_proxy-0.2.1.dist-info/WHEEL
localstack_extension_aws_proxy-0.2.1.dist-info/entry_points.txt
localstack_extension_aws_proxy-0.2.1.dist-info/top_level.txt
localstack_extension_aws_proxy-0.2.1.dist-info/RECORD
