Metadata-Version: 2.4
Name: localstack-extension-aws-proxy
Version: 0.2.1
Summary: LocalStack AWS Cloud Proxy
Home-page: https://github.com/localstack/localstack-extensions/tree/main/aws-proxy
Author: LocalStack Team
Author-email: info@localstack.cloud
Requires-Dist: boto3>=1.26.151
Requires-Dist: botocore>=1.29.151
Requires-Dist: flask
Requires-Dist: localstack-client
Requires-Dist: xmltodict
Requires-Dist: hypercorn
Requires-Dist: h11
Requires-Dist: quart
Requires-Dist: boto
Requires-Dist: cbor2
Requires-Dist: flask-cors
Requires-Dist: jsonpatch
Requires-Dist: moto
Requires-Dist: werkzeug
Provides-Extra: test
Requires-Dist: apispec; extra == "test"
Requires-Dist: localstack-core; extra == "test"
Requires-Dist: localstack-ext; extra == "test"
Requires-Dist: openapi-spec-validator; extra == "test"
Requires-Dist: pyproject-flake8; extra == "test"
Requires-Dist: pytest; extra == "test"
Requires-Dist: pytest-httpserver; extra == "test"
Requires-Dist: rolo; extra == "test"
